Workbook

Sheet 00_overview
A1: 万科企业股份有限公司 2025年半年度附注优先分析底稿
A2: 来源：ChinaMoney 发现 + CNInfo 回退下载；MinerU 解析；financial-analyzer 生成底稿后人工正式化。
A4: 执行摘要
A5: 上半年营业收入 1,053.23 亿元，同比下降 26.23%；归母净亏损 119.47 亿元；经营活动现金流净额 -30.39 亿元。账面现金 740.02 亿元，但受限资金 46.55 亿元，按近端到期债务口径现金覆盖率仅 0.52x，按可动用现金口径约 0.52x?
A8: 关键结论
A9: 主体仍处于“高体量资产、高杠杆、高抵押、低现金创造”的状态。短期违约信号未显性化，但流动性稳定依赖深铁支持、再融资接续和项目去化。
A12: 核心指标
A13: 指标 | B13: 2025H1 | C13: 2024H1/2024YE | D13: 变化/比率 | E13: 解读
A14: 营业收入(亿元) | B14: =RAW_00_overview!B14 | C14: =RAW_00_overview!C14 | D14: =B14/C14-1 | E14: 收入下滑
A15: 归母净利润(亿元) | B15: =RAW_00_overview!B15 | C15: =RAW_00_overview!C15 | D15: =B15/C15-1 | E15: 亏损扩大
A16: 经营现金流(亿元) | B16: =RAW_00_overview!B16 | C16: =RAW_00_overview!C16 | D16: =B16/C16-1 | E16: 仍为负
A17: 可动用现金(亿元) | B17: =RAW_00_overview!B17 | C17: =RAW_00_overview!C17 | D17: =B17/C17 | E17: 剔除受限资金
A18: 近端到期债务(亿元) | B18: =RAW_00_overview!B18 | C18: =RAW_00_overview!C18 | E18: 短债+一年内到期借款/债券/租赁/利息
A19: 存货净额(亿元) | B19: =RAW_00_overview!B19 | C19: =RAW_00_overview!C19 | D19: =B19/C19 | E19: 计提减值 152.41 亿元
A20: 其他应收款净额(亿元) | B20: =RAW_00_overview!B20 | C20: =RAW_00_overview!C20 | D20: =B20/C20 | E20: 97.47% 单项计提
A21: 合同负债(亿元) | B21: =RAW_00_overview!B21 | C21: =RAW_00_overview!C21 | D21: =B21/C21 | E21: 一年以上占 44.58%
A23: 阅读顺序
A24: 先看现金、债务和合同负债，再看其他应收、存货和投资性房地产，最后回到利润表补充资料和现金流量表补充资料。

Sheet 01_kpi_dashboard
A1: KPI Dashboard
A2: 用于快速扫描收入、利润、现金和杠杆四条主线。
A4: 分类 | B4: 指标 | C4: 2025H1 | D4: 2024H1/2024YE | E4: 变化 | F4: 单位 | G4: 风险判断
A5: 盈利 | B5: 营业收入 | C5: 1053.233 | D5: 1427.7876 | E5: -0.26233215 | F5: 亿元 | G5: 收入明显下行
A6: 盈利 | B6: 归母净利润 | C6: -119.46574 | D6: -98.524996 | E6: -0.21254242 | F6: 亿元 | G6: 亏损扩大
A7: 盈利 | B7: ROE | C7: -0.0607 | F7: % | G7: 股东回报为负
A8: 现金 | B8: 经营活动现金流 | C8: -30.387046 | D8: -51.763258 | E8: 0.4129611 | F8: 亿元 | G8: 仍为负
A9: 流动性 | B9: 可动用现金 | C9: 693.47563 | D9: 740.02264 | E9: 0.5147797 | F9: 亿元/x | G9: 覆盖不足
A10: 流动性 | B10: 近端到期债务 | C10: 1347.1309 | D10: 1460.4557 | F10: 亿元 | G10: 再融资压力大
A11: 融资 | B11: 半年名义融资成本率 | C11: 0.019 | F11: % | G11: 不含资本化利息
A12: 融资 | B12: 半年融资成本率（含资本化） | C12: 0.026441897 | F12: % | G12: 按平均有息债务规模口径
A13: 融资 | B13: 年化融资成本率 | C13: 0.052883794 | F13: % | G13: 按平均有息债务规模折年
A14: 资产质量 | B14: 其他应收款净额 | C14: 2152.5982 | D14: 2213.5959 | E14: 0.11589834 | F14: 亿元 | G14: 沉淀资金高
A15: 资产质量 | B15: 存货净额 | C15: 4625.1854 | D15: 5190.0944 | E15: 0.032951817 | F15: 亿元 | G15: 去化与减值并存
A16: 资产质量 | B16: 投资性房地产净额 | C16: 1373.6254 | D16: 1410.5737 | E16: 0.58273536 | F16: 亿元 | G16: 抵押深度高
A17: 资产质量 | B17: 合同负债 | C17: 1580.0312 | D17: 1923.6111 | E17: 0.44582657 | F17: 亿元 | G17: 预收款仍是周转源

Sheet 02_financial_summary
A1: Financial Summary
A2: 收入、利润、每股和现金流的低频摘要。
A4: 利润表摘要
A5: 项目 | B5: 期间 | C5: 数值 | D5: 单位 | E5: 说明
A6: 营业收入 | B6: 2025H1 | C6: 1053.233 | D6: 亿元 | E6: 同比 -26.23%
A7: 投资收益 | B7: 2025H1 | C7: -5.679801 | D7: 亿元 | E7: 损失
A8: 营业收入/归母净利润 | B8: 2025H1 | C8: 8.8161934 | D8: 倍 | E8: 营收仍覆盖不了亏损规模
A9: 归母净利润 | B9: 2025H1 | C9: -119.46574 | D9: 亿元 | E9: 亏损
A10: 基本每股收益 | B10: 2025H1 | C10: -1.01 | D10: 元 | E10: 为负
A11: ROE | B11: 2025H1 | C11: -0.0607 | D11: % | E11: 为负
A13: 现金流摘要
A14: 项目 | B14: 期间 | C14: 数值 | D14: 单位 | E14: 说明
A15: 经营活动现金流净额 | B15: 2025H1 | C15: -30.387046 | D15: 亿元 | E15: 仍为负
A16: 购买/收回理财产品 | B16: 2025H1 | C16: 1.6270308 | D16: 亿元 | E16: 现金管理
A17: 收到利息收入 | B17: 2025H1 | C17: 3.4169678 | D17: 亿元 | E17: 资金收益
A18: 融资活动负债净变动 | B18: 2025H1 | C18: 1.4658745 | D18: 亿元 | E18: 筹资活动净增
A20: 资产负债表摘要
A21: 项目 | B21: 期间 | C21: 数值 | D21: 单位 | E21: 说明
A22: 总资产 | B22: 2025H1 | C22: 11941.489 | D22: 亿元 | E22: 资产规模仍大
A23: 总负债 | B23: 2025H1 | C23: 8729.8833 | D23: 亿元 | E23: 高杠杆
A24: 股东权益 | B24: 2025H1 | C24: 1914.4082 | D24: 亿元 | E24: 仍为正
A25: 资产负债率 | B25: 2025H1 | C25: 0.73105485 | D25: % | E25: 杠杆偏高

Sheet 03_debt_profile
A1: Debt Profile
A2: 近端债务、长期债务、债券和租赁负债的结构化拆分。
A4: 近端到期压力
A5: 项目 | B5: 期间 | C5: 数值 | D5: 单位 | E5: 备注
A6: 一年内到期的长期借款 | B6: 2025H1 | C6: =RAW_03_debt_profile!C6 | D6: 亿元 | E6: 无逾期借款
A7: 一年内到期的应付债券 | B7: 2025H1 | C7: =RAW_03_debt_profile!C7 | D7: 亿元 | E7: 兑付压力
A8: 一年内到期的租赁负债 | B8: 2025H1 | C8: =RAW_03_debt_profile!C8 | D8: 亿元 | E8: 广义杠杆
A9: 一年内到期的应付利息 | B9: 2025H1 | C9: =RAW_03_debt_profile!C9 | D9: 亿元 | E9: 现金消耗
A10: 近端到期债务合计 | B10: 2025H1 | C10: =SUM(C6:C9) | D10: 亿元 | E10: 关键压力口径
A12: 长期债务
A13: 项目 | B13: 期间 | C13: 数值 | D13: 单位 | E13: 备注
A14: 长期借款净额 | B14: 2025H1 | C14: =RAW_03_debt_profile!C14 | D14: 亿元 | E14: 含各种抵押/信用/质押
A15: 应付债券净额 | B15: 2025H1 | C15: =RAW_03_debt_profile!C15 | D15: 亿元 | E15: 公开债为主
A16: 租赁负债净额 | B16: 2025H1 | C16: =RAW_03_debt_profile!C16 | D16: 亿元 | E16: 广义债务
A17: 有息债务规模（平均） | B17: 2025H1 | C17: =RAW_03_debt_profile!C17 | D17: 亿元 | E17: 期初与期末余额平均
A18: 经调整净债务 | B18: 2025H1 | C18: =RAW_03_debt_profile!C18 | D18: 亿元 | E18: 总债务减货币资金
A20: 融资成本
A21: 项目 | B21: 期间 | C21: 数值 | D21: 单位 | E21: 备注
A22: 贷款、债券及应付款项的利息支出 | B22: 2025H1 | C22: =RAW_03_debt_profile!C22 | D22: 亿元 | E22: 附注46，含未资本化部分
A23: 租赁负债的利息支出 | B23: 2025H1 | C23: =RAW_03_debt_profile!C23 | D23: 亿元 | E23: 附注46
A24: 小计：名义利息支出 | B24: 2025H1 | C24: =SUM(C22:C23) | D24: 亿元 | E24: 借款、债券及应付款项利息 + 租赁利息
A25: 减：资本化利息 | B25: 2025H1 | C25: =RAW_03_debt_profile!C25 | D25: 亿元 | E25: 回到真实融资成本池
A26: 半年度融资成本（含资本化） | B26: 2025H1 | C26: =C24+C25 | D26: 亿元 | E26: 融资成本分子
A27: 年化融资成本率 | B27: 2025H1x2 | C27: =C26/C17 | D27: % | E27: 按平均有息债务规模口径折年
A29: 资本结构
A30: 项目 | B30: 期间 | C30: 数值 | D30: 单位 | E30: 备注
A31: 股东权益 | B31: 2025H1 | C31: =RAW_03_debt_profile!C31 | D31: 亿元 | E31: 分母
A32: 净债务/股东权益 | B32: 2025H1 | C32: =C18/C31 | D32: x | E32: 约 90.4%
A33: 总债务/股东权益 | B33: 2025H1 | C33: =C17/C31 | D33: x | E33: 约 113.4%
A34: 管理层披露财务契约借款规模 | B34: 2025H1 | C34: =RAW_03_debt_profile!C34 | D34: 亿元 | E34: 未触发实时偿还

Sheet 04_liquidity_and_covenants
A1: Liquidity and Covenants
A2: 现金、受限资产、管理层支持和契约约束放在同一页看。
A4: 现金与覆盖
A5: 项目 | B5: 期间 | C5: 数值 | D5: 单位 | E5: 备注
A6: 现金及现金等价物 | B6: 2025H1 | C6: 740.02264 | D6: 亿元 | E6: 名义现金
A7: 受限资金 | B7: 2025H1 | C7: 46.54701 | D7: 亿元 | E7: 不可自由动用
A8: 可动用现金 | B8: 2025H1 | C8: 693.47563 | D8: 亿元 | E8: 用于偿债覆盖
A9: 近端到期债务 | B9: 2025H1 | C9: 1347.1309 | D9: 亿元 | E9: 关键压力口径
A10: 现金覆盖率 | B10: 2025H1 | C10: 0.5147797 | D10: x | E10: 覆盖不足 1 倍
A12: 管理层支持
A13: 管理层在报告中披露：深铁集团累计向公司提供 238.8 亿元股东借款；上半年已完成 243.9 亿元公开债务偿还；2027 年之前无境外公开债到期。
A16: 契约与窗口
A17: 项目 | B17: 期间 | C17: 数值 | D17: 单位 | E17: 备注
A18: 附财务契约借款规模 | B18: 2025H1 | C18: 103.944 | D18: 亿元 | E18: 涉及财务比率约束
A19: 未逾期的一年内到期长期借款 | B19: 2025H1 | C19: 1039.537 | D19: 亿元 | E19: 公司明确披露无逾期
A20: 资本结构总债务 | B20: 2025H1 | C20: 3642.5768 | D20: 亿元 | E20: 管理层口径

Sheet 05_asset_quality
A1: Asset Quality
A2: 重点看“可变现性”和“是否被抵押”，不是只看账面规模。
A4: 核心资产
A5: 项目 | B5: 期间 | C5: 数值 | D5: 单位 | E5: 判断
A6: 应收账款净额 | B6: 2025H1 | C6: 93.121589 | D6: 亿元 | E6: 坏账率 10.92%
A7: 其他应收款净额 | B7: 2025H1 | C7: 2152.5982 | D7: 亿元 | E7: 单项计提占比 97.47%
A8: 合同资产 | B8: 2025H1 | C8: 123.37821 | D8: 亿元 | E8: 政府/相关方为主
A9: 其他流动资产 | B9: 2025H1 | C9: 127.01757 | D9: 亿元 | E9: 合同取得成本 + 待抵扣增值税
A10: 存货净额 | B10: 2025H1 | C10: 4625.1854 | D10: 亿元 | E10: 减值率 3.30%
A11: 存货抵押/担保 | B11: 2025H1 | C11: 627.4711 | D11: 亿元 | E11: 占存货净额 13.57%
A12: 投资性房地产净额 | B12: 2025H1 | C12: 1373.6254 | D12: 亿元 | E12: 抵押占比 58.27%
A13: 未办妥产权证的投资性房地产 | B13: 2025H1 | C13: 78.719755 | D13: 亿元 | E13: 产权手续未完结
A14: 合同负债 | B14: 2025H1 | C14: 1580.0312 | D14: 亿元 | E14: 一年以上占 44.58%
A15: 预付款项（重大一年以上） | B15: 2025H1 | C15: 84.47 | D15: 亿元 | E15: 旧改项目前期款
A17: 资产质量结论
A18: 账面资产很大，但其他应收和存货两大科目都存在明显沉淀和减值压力，投资性房地产又被大比例抵押。可动用资产与账面资产之间的差距，是本期信用分析的核心。

Sheet 06_cash_flow_bridge
A1: Cash Flow Bridge
A2: 从附注和利润补充资料里，挑出影响现金流的关键桥梁。
A4: 利润到现金
A5: 项目 | B5: 期间 | C5: 数值 | D5: 单位 | E5: 说明
A6: 归母净亏损 | B6: 2025H1 | C6: =RAW_06_cash_flow_bridge!C6 | D6: 亿元 | E6: 利润端起点
A7: 资产减值损失 | B7: 2025H1 | C7: =RAW_06_cash_flow_bridge!C7 | D7: 亿元 | E7: 利润补充资料
A8: 信用减值损失 | B8: 2025H1 | C8: =RAW_06_cash_flow_bridge!C8 | D8: 亿元 | E8: 应收风险仍在
A9: 投资收益(损失) | B9: 2025H1 | C9: =RAW_06_cash_flow_bridge!C9 | D9: 亿元 | E9: 非经常性波动
A10: 经营活动现金流净额 | B10: 2025H1 | C10: =RAW_06_cash_flow_bridge!C10 | D10: 亿元 | E10: 现金流结果
A11: 经营现金流补充说明 | B11: 2025H1 | C11: =RAW_06_cash_flow_bridge!C11 | D11: — | E11: 净亏损、减值和营运资产变化共同解释
A13: 筹资活动
A14: 项目 | B14: 期间 | C14: 数值 | D14: 单位 | E14: 说明
A15: 短期借款期末余额 | B15: 2025H1 | C15: =RAW_06_cash_flow_bridge!C15 | D15: 亿元 | E15: 滚动融资
A16: 长期借款(含一年内到期) | B16: 2025H1 | C16: =RAW_06_cash_flow_bridge!C16 | D16: 亿元 | E16: 筹资活动净变动后口径
A17: 应付债券(含一年内到期) | B17: 2025H1 | C17: =RAW_06_cash_flow_bridge!C17 | D17: 亿元 | E17: 公开债滚动
A18: 租赁负债(含一年内到期) | B18: 2025H1 | C18: =RAW_06_cash_flow_bridge!C18 | D18: 亿元 | E18: 广义负债

Sheet 07_notes_map
A1: Notes Map
A2: 选取最重要的附注章节，作为正式成稿的证据底座。
A4: 章号 | B4: 章节 | C4: 行范围 | D4: 关键摘要 | E4: 主题标签
A5: 1 | B5: 1 货币资金 | C5: 2429-2436 | D5: # 1、货币资金 人民币元 项目 2025年6月30日 2024年12月31日 原币 折算汇率 折合人民币 原币 折算汇率 折合人民币 库存现金： 人民币 6,445,748.27 1.0000 6,445,748.27 8,191,876 | E5: cash, restricted_assets, risk_management
A6: 3 | B6: 3 应收账款 | C6: 2441-2489 | D6: # 3、应收账款 (1)按账龄披露 人民币元 账龄 2025 年 6 月 30 日 2024 年 12 月 31 日 1 年以内 7,486,866,135.33 6,615,983,196.98 1 至 3 年 1,977,310,462 | E6: debt, 应收账款
A7: 5 | B7: 5 其他应收款 | C7: 2497-2559 | D7: # 5、其他应收款 # 5.1项目列示 人民币元 项目 2025 年 6 月 30 日 2024 年 12 月 31 日 应收利息 - 523,370.83 应收股利 288,938,655.44 65,137,259.06 其他应收款 2 | E7: debt, liquidity, restricted_assets
A8: 6 | B8: 6 存货 | C8: 2560-2757 | D8: # 6、存货 # (1)存货分类 人民币元 项目 2025年6月30日 2024年12月31日 账面余额 存货跌价准备 账面价值 账面余额 存货跌价准备 账面价值 已完工开发产品 119,436,183,839.77 2,301,779,1 | E8: debt, investment_property, restricted_assets
A9: 7 | B9: 7 合同资产 | C9: 2758-2777 | D9: # 7、合同资产 # (1)合同资产情况 人民币元 项目 2025年6月30日 2024年12月31日 账面余额 坏账准备 账面价值 账面余额 坏账准备 账面价值 建造合同 12,337,821,477.85 - 12,337,821,47 | E9: risk_management, 合同资产
A10: 8 | B10: 8 其他流动资产 | C10: 2778-2793 | D10: # 8、其他流动资产 人民币元 项目 2025 年 6 月 30 日 2024 年 12 月 31 日 合同取得成本 3,602,985,345.65 4,126,870,606.04 待抵扣增值税 9,098,771,840.65 9,2 | E10: profitability, liquidity, 其他流动资产
A11: 12 | B11: 12 投资性房地产 | C11: 2830-2842 | D11: # 12、投资性房地产 # (1)采用成本计量模式的投资性房地产 人民币元 项目 已完工 在建 合计 一、账面原值 1.2025年1月1日 143,974,575,048.36 11,234,769,985.31 155,209,345,0 | E11: debt, restricted_assets, external_guarantees
A12: 25 | B12: 24 应付账款 | C12: 2981-2988 | D12: # 24、应付账款 人民币元 项目 2025 年 6 月 30 日 2024 年 12 月 31 日 应付地价 16,009,433,338.20 16,840,960,350.23 应付及预提工程款 106,600,741,232.58 | E12: restricted_assets, 应付账款
A13: 29 | B13: 28 其他应付款 | C13: 3037-3068 | D13: # 28、其他应付款 # 28.1 项目列示 人民币元 项目 2025 年 6 月 30 日 2024 年 12 月 31 日 应付利息 48,634,934.82 114,078,222.03 应付股利 267,927,565.70 27 | E13: debt, profitability, restricted_assets
A14: 31 | B14: 30 其他流动负债 | C14: 3081-3088 | D14: # 30、其他流动负债 人民币元 项目 2025 年 6 月 30 日 2024 年 12 月 31 日 待转销项税(注) 14,641,509,761.17 17,750,017,552.59 合计 14,641,509,761.17 1 | E14: liquidity, 其他流动负债
A15: 32 | B15: 31 长期借款 | C15: 3089-3121 | D15: # 31、长期借款 # (1)长期借款分类 人民币元 项目 2025年6月30日 原币 汇率 折人民币 借款条件 银行借款 人民币 62,505,632,279.44 1.0000 62,505,632,279.44 信用(注1) 88,0 | E15: debt, profitability, liquidity
A16: 33 | B16: 32 应付债券 | C16: 3122-3143 | D16: # 32、应付债券 (1)应付债券的具体情况(不包括划分为金融负债的优先股、永续债等其他金融工具) 人民币元 债券名称 币种 面值(亿元) 发行日期 债券期限 债券利率 发行金额 2025年1月1日 2025年1月1日 本期发行 按面值计提 | E16: debt, liquidity, risk_management
... A26: 93 | B26: 3 境内外会计准则下会计数据差异 | C26: 4147-4155 | D26: # 3、境内外会计准则下会计数据差异 (1)同时按照国际会计准则与按照中国会计准则披露的财务报告中净亏损和净资产差异情况 人民币元 归属于母公司股东的净亏损 归属于母公司股东的净资产 2025年1月1日至6月30日止期间 2024年1月1日 | E26: governance, 境内外会计准则下会计数据差异

Sheet 08_management_support
A1: Management Support
A2: 管理层披露的股东支持、债务到期和再融资窗口。
A4: 支持与窗口
A5: 事项 | B5: 来源 | C5: 数值 | D5: 单位 | E5: 说明
A6: 深铁股东借款累计 | B6: 报告正文 | C6: 238.8 | D6: 亿元 | E6: 流动性支撑
A7: 公开债务偿还 | B7: 报告正文 | C7: 243.9 | D7: 亿元 | E7: 已完成
A8: 境外公开债到期 | B8: 报告正文 | C8: 0 | D8: 年内 | E8: 2027 年前无到期
A9: 管理层对流动性判断 | B9: 报告正文 | C9: 0 | D9: — | E9: 以支持+再融资缓冲短期风险
A11: 原文摘要
A12: 管理层披露：深铁集团在上半年继续提供流动性支持，累计股东借款 238.8 亿元；公司已完成 243.9 亿元公开债务偿还；2027 年之前无境外公开债到期。

Sheet 09_capital_structure
A1: Capital Structure
A2: 管理层资本结构口径，结合总债务和净债务观察杠杆。
A4: 资本结构
A5: 项目 | B5: 期间 | C5: 数值 | D5: 单位 | E5: 备注
A6: 总债务合计 | B6: 2025H1 | C6: 3642.5768 | D6: 亿元 | E6: 管理层口径
A7: 货币资金 | B7: 2025H1 | C7: 740.02264 | D7: 亿元 | E7: 扣减项
A8: 经调整净债务 | B8: 2025H1 | C8: 2902.5542 | D8: 亿元 | E8: 总债务减现金
A9: 股东权益 | B9: 2025H1 | C9: 3211.6054 | D9: 亿元 | E9: 分母
A10: 净债务/股东权益 | B10: 2025H1 | C10: 0.90377047 | D10: x | E10: 接近 0.90x
A11: 总债务/股东权益 | B11: 2025H1 | C11: 1.1341919 | D11: x | E11: 接近 1.13x

Sheet 99_evidence_index
A1: Evidence Index
A2: 证据索引用于回溯各表格中的关键数字。
A4: 证据ID | B4: 章节 | C4: 证据摘要 | D4: 来源区间 | E4: 用途
A5: EVD-0001 | B5: 1 1 货币资金 | C5: 货币资金、受限资金、境外存款 | D5: 2429-2436 | E5: 现金与受限资金
A6: EVD-0002 | B6: 3 3 应收账款 | C6: 应收账款坏账率与账龄 | D6: 2441-2489 | E6: 回款风险
A7: EVD-0003 | B7: 5 5 其他应收款 | C7: 其他应收款单项计提 97.47% | D7: 2497-2559 | E7: 沉淀资金
A8: EVD-0004 | B8: 6 6 存货 | C8: 存货减值 152.41 亿元、抵押 62.75 亿元 | D8: 2560-2757 | E8: 库存与抵押
A9: EVD-0005 | B9: 7 7 合同资产 | C9: 合同资产 123.38 亿元 | D9: 2758-2777 | E9: 合同结算
A10: EVD-0006 | B10: 8 8 其他流动资产 | C10: 合同取得成本与待抵扣增值税 | D10: 2778-2793 | E10: 流动资产
A11: EVD-0007 | B11: 12 12 投资性房地产 | C11: 投资性房地产 1,373.63 亿元，抵押 800.46 亿元 | D11: 2830-2842 | E11: 商业资产
A12: EVD-0008 | B12: 25 24 应付账款 | C12: 合同负债 1,580.03 亿元，一年以上 704.42 亿元 | D12: 2989-3006 | E12: 预收房款
A13: EVD-0009 | B13: 29 28 其他应付款 | C13: 一年内到期的非流动负债 1,347.13 亿元 | D13: 3069-3080 | E13: 近端债务
A14: EVD-0010 | B14: 31 30 其他流动负债 | C14: 长期借款 1,780.51 亿元，契约借款 1,039.44 亿元 | D14: 3089-3121 | E14: 银行借款
A15: EVD-0011 | B15: 32 31 长期借款 | C15: 应付债券净额 436.02 亿元，一年内到期 273.59 亿元 | D15: 3122-3143 | E15: 债券兑付
... A22: EVD-0018 | B22: 47 46 财务费用 | C22: 名义利息 72.57 亿元，资本化利息 32.15 亿元，按期初期末平均有息债务口径，含资本化后半年融资成本约 2.63%，折年约 5.26% | D22: 3267-3272 | E22: 融资成本

Sheet RAW_00_overview
A1: 万科企业股份有限公司 2025年半年度附注优先分析底稿
A2: 来源：ChinaMoney 发现 + CNInfo 回退下载；MinerU 解析；financial-analyzer 生成底稿后人工正式化。
A4: 执行摘要
A5: 上半年营业收入 1,053.23 亿元，同比下降 26.23%；归母净亏损 119.47 亿元；经营活动现金流净额 -30.39 亿元。账面现金 740.02 亿元，但受限资金 46.55 亿元，按近端到期债务口径现金覆盖率仅 0.52x，按可动用现金口径约 0.52x?
A8: 关键结论
A9: 主体仍处于“高体量资产、高杠杆、高抵押、低现金创造”的状态。短期违约信号未显性化，但流动性稳定依赖深铁支持、再融资接续和项目去化。
A12: 核心指标
A13: 指标 | B13: 2025H1 | C13: 2024H1/2024YE | D13: 变化/比率 | E13: 解读
A14: 营业收入(亿元) | B14: 1053.233 | C14: 1427.7876 | D14: -0.26233215 | E14: 收入下滑
A15: 归母净利润(亿元) | B15: -119.46574 | C15: -98.524996 | D15: -0.21254242 | E15: 亏损扩大
A16: 经营现金流(亿元) | B16: -30.387046 | C16: -51.763258 | D16: 0.4129611 | E16: 仍为负
A17: 可动用现金(亿元) | B17: 693.47563 | C17: 740.02264 | D17: 0.5147797 | E17: 剔除受限资金
A18: 近端到期债务(亿元) | B18: 1347.1309 | C18: 1460.4557 | E18: 短债+一年内到期借款/债券/租赁/利息
A19: 存货净额(亿元) | B19: 4625.1854 | C19: 5190.0944 | D19: 0.032951817 | E19: 计提减值 152.41 亿元
A20: 其他应收款净额(亿元) | B20: 2152.5982 | C20: 2213.5959 | D20: 0.11589834 | E20: 97.47% 单项计提
A21: 合同负债(亿元) | B21: 1580.0312 | C21: 1923.6111 | D21: 0.44582657 | E21: 一年以上占 44.58%
A23: 阅读顺序
A24: 先看现金、债务和合同负债，再看其他应收、存货和投资性房地产，最后回到利润表补充资料和现金流量表补充资料。

Sheet RAW_03_debt_profile
A1: Debt Profile
A2: 近端债务、长期债务、债券和租赁负债的结构化拆分。
A4: 近端到期压力
A5: 项目 | B5: 期间 | C5: 数值 | D5: 单位 | E5: 备注
A6: 一年内到期的长期借款 | B6: 2025H1 | C6: 1039.537 | D6: 亿元 | E6: 无逾期借款
A7: 一年内到期的应付债券 | B7: 2025H1 | C7: 273.58717 | D7: 亿元 | E7: 兑付压力
A8: 一年内到期的租赁负债 | B8: 2025H1 | C8: 17.903115 | D8: 亿元 | E8: 广义杠杆
A9: 一年内到期的应付利息 | B9: 2025H1 | C9: 16.103592 | D9: 亿元 | E9: 现金消耗
A10: 近端到期债务合计 | B10: 2025H1 | C10: 1347.1309 | D10: 亿元 | E10: 关键压力口径
A12: 长期债务
A13: 项目 | B13: 期间 | C13: 数值 | D13: 单位 | E13: 备注
A14: 长期借款净额 | B14: 2025H1 | C14: 1780.5132 | D14: 亿元 | E14: 含各种抵押/信用/质押
A15: 应付债券净额 | B15: 2025H1 | C15: 436.02038 | D15: 亿元 | E15: 公开债为主
A16: 租赁负债净额 | B16: 2025H1 | C16: 157.53855 | D16: 亿元 | E16: 广义债务
A17: 有息债务规模（平均） | B17: 2025H1 | C17: 3960.3159 | D17: 亿元 | E17: 期初与期末余额平均
A18: 经调整净债务 | B18: 2025H1 | C18: 2902.5542 | D18: 亿元 | E18: 总债务减货币资金
A20: 融资成本
A21: 项目 | B21: 期间 | C21: 数值 | D21: 单位 | E21: 备注
A22: 贷款、债券及应付款项的利息支出 | B22: 2025H1 | C22: 69.114003 | D22: 亿元 | E22: 附注46，含未资本化部分
A23: 租赁负债的利息支出 | B23: 2025H1 | C23: 3.4588099 | D23: 亿元 | E23: 附注46
A24: 小计：名义利息支出 | B24: 2025H1 | C24: 72.572812 | D24: 亿元 | E24: 借款、债券及应付款项利息 + 租赁利息
A25: 减：资本化利息 | B25: 2025H1 | C25: -32.145453 | D25: 亿元 | E25: 回到真实融资成本池
A26: 半年度融资成本（含资本化） | B26: 2025H1 | C26: 104.71827 | D26: 亿元 | E26: 融资成本分子
A27: 年化融资成本率 | B27: 2025H1x2 | C27: 0.052883794 | D27: % | E27: 按平均有息债务规模口径折年
A29: 资本结构
A30: 项目 | B30: 期间 | C30: 数值 | D30: 单位 | E30: 备注
A31: 股东权益 | B31: 2025H1 | C31: 3211.6054 | D31: 亿元 | E31: 分母
A32: 净债务/股东权益 | B32: 2025H1 | C32: 0.90377047 | D32: x | E32: 约 90.4%
A33: 总债务/股东权益 | B33: 2025H1 | C33: 1.1341919 | D33: x | E33: 约 113.4%
A34: 管理层披露财务契约借款规模 | B34: 2025H1 | C34: 103.944 | D34: 亿元 | E34: 未触发实时偿还

Sheet RAW_06_cash_flow_bridge
A1: Cash Flow Bridge
A2: 从附注和利润补充资料里，挑出影响现金流的关键桥梁。
A4: 利润到现金
A5: 项目 | B5: 期间 | C5: 数值 | D5: 单位 | E5: 说明
A6: 归母净亏损 | B6: 2025H1 | C6: -119.46574 | D6: 亿元 | E6: 利润端起点
A7: 资产减值损失 | B7: 2025H1 | C7: 51.451847 | D7: 亿元 | E7: 利润补充资料
A8: 信用减值损失 | B8: 2025H1 | C8: 3.0165135 | D8: 亿元 | E8: 应收风险仍在
A9: 投资收益(损失) | B9: 2025H1 | C9: -5.679801 | D9: 亿元 | E9: 非经常性波动
A10: 经营活动现金流净额 | B10: 2025H1 | C10: -30.387046 | D10: 亿元 | E10: 现金流结果
A11: 经营现金流补充说明 | B11: 2025H1 | C11: 0 | D11: — | E11: 净亏损、减值和营运资产变化共同解释
A13: 筹资活动
A14: 项目 | B14: 期间 | C14: 数值 | D14: 单位 | E14: 说明
A15: 短期借款期末余额 | B15: 2025H1 | C15: 231.15624 | D15: 亿元 | E15: 滚动融资
A16: 长期借款(含一年内到期) | B16: 2025H1 | C16: 282.00502 | D16: 亿元 | E16: 筹资活动净变动后口径
A17: 应付债券(含一年内到期) | B17: 2025H1 | C17: 709.60756 | D17: 亿元 | E17: 公开债滚动
A18: 租赁负债(含一年内到期) | B18: 2025H1 | C18: 175.44167 | D18: 亿元 | E18: 广义负债
